sid_provision/__init__.py
sid_provision/config/nordic/nrf528xx_dk/config.yaml
sid_provision/config/nordic/nrf528xx_dk/config_legacy.yaml
sid_provision/config/ti/cc13x2_26x2/config.yaml
sid_provision/config/ti/cc13x2_26x2/config_legacy.yaml
sid_provision/run.py
sid_provision-0.2.3.dist-info/LICENSE
sid_provision-0.2.3.dist-info/METADATA
sid_provision-0.2.3.dist-info/NOTICE
sid_provision-0.2.3.dist-info/WHEEL
sid_provision-0.2.3.dist-info/entry_points.txt
sid_provision-0.2.3.dist-info/RECORD
