Metadata-Version: 2.1
Name: sid_provision
Version: 0.2.3
Summary: Tool generate mfg pages
Author: Sidewalk Team
Author-email: sidewalk-provisioning@amazon.com
Requires-Python: >=3.8,<4.0
Classifier: Programming Language :: Python :: 3
Classifier: Programming Language :: Python :: 3.8
Classifier: Programming Language :: Python :: 3.9
Classifier: Programming Language :: Python :: 3.10
Classifier: Programming Language :: Python :: 3.11
Classifier: Programming Language :: Python :: 3.12
Requires-Dist: PyYAML (>=6.0,<7.0)
Requires-Dist: intelhex (>=2.3.0,<3.0.0)
